pyhessian/__init__.py
pyhessian/hessian.py
pyhessian/utils.py
PyHessian-0.1.dist-info/LICENSE
PyHessian-0.1.dist-info/METADATA
PyHessian-0.1.dist-info/WHEEL
PyHessian-0.1.dist-info/top_level.txt
PyHessian-0.1.dist-info/RECORD
