Metadata-Version: 2.1
Name: PyHessian
Version: 0.1
Summary: Pytorch library for second-order based analysis and training of Neural Networks
Home-page: https://https://github.com/amirgholami/PyHessian
Author: Zhewei Yao, Amir Gholami
Author-email: zheweiy@berkeley.edu, amirgh@berkeley.edu
License: MIT
Platform: UNKNOWN
Requires-Dist: numpy
Requires-Dist: torch
